dep_manager/__init__.py
dep_manager/cli.py
dep_manager_cli-0.1.1.dist-info/METADATA
dep_manager_cli-0.1.1.dist-info/WHEEL
dep_manager_cli-0.1.1.dist-info/entry_points.txt
dep_manager_cli-0.1.1.dist-info/top_level.txt
dep_manager_cli-0.1.1.dist-info/RECORD
